{
    "logic": "pl",
    "rule": "MP",
    "depth": "d1",
    "samples": [
        {
            "id": 1,
            "context": "If James studies hard for his chemistry exam, he will likely get a good grade. James has been diligently reviewing his notes and practicing problems every night this week. James studies hard for his exam.",
            "question": "Will James get a good grade?",
            "answer": "yes"
        },
        {
            "id": 2,
            "context": "Whenever Katie follows a recipe precisely, the dish usually turns out well. Katie carefully measured each ingredient and followed all the cooking instructions to prepare her grandmother's lasagna recipe. Katie followed the recipe exactly.",
            "question": "Did the lasagna turn out well?",
            "answer": "yes"
        },
        {
            "id": 3,
            "context": "If Sam waters his vegetable garden regularly, the plants will be healthy and productive. Sam made sure to thoroughly water the garden twice a week, even in hot weather. Sam waters the garden regularly.",
            "question": "Are Sam's vegetable plants healthy and productive?",
            "answer": "yes"
        },
        {
            "id": 4,
            "context": "When a company invests in employee training, there is often an increase in productivity. The management dedicated funding to comprehensive training seminars for all new hires. The company invested in employee training.",
            "question": "Did productivity increase?",
            "answer": "yes"
        },
        {
            "id": 5,
            "context": "If Jenny gets enough sleep, she is usually energetic and focused throughout the day. Last night, Jenny made sure to get to bed early and got a full 8 hours of rest. Jenny got adequate sleep.",
            "question": "Is Jenny energetic and focused today?",
            "answer": "yes"
        },
        {
            "id": 6,
            "context": "If Alex studies hard for his math test, he will likely get a good grade. Alex has been hitting the books every night to prepare for his big test tomorrow. Alex studies diligently for his math test.",
            "question": "Will Alex probably get a good grade?",
            "answer": "yes"
        },
        {
            "id": 7,
            "context": "If Jenny consistently shows up on time for work, her boss will be happy with her performance. Jenny makes sure to wake up early and plan her commute so she never arrives late. Jenny is always punctual for her job.",
            "question": "Is Jenny's boss satisfied with her timeliness?",
            "answer": "yes"
        },
        {
            "id": 8,
            "context": "If Mark eats a healthy diet, he will have more energy throughout the day. Today, Mark opts for oatmeal, fruits, vegetables, and grilled chicken to fuel himself properly. Mark eats nutritious foods.",
            "question": "Does Mark tend to feel energetic daily?",
            "answer": "yes"
        },
        {
            "id": 9,
            "context": "If the team collaborates effectively, they will create a successful product. During their morning standup, the engineers discussed strategies for working together seamlessly. The team coordinates smoothly.",
            "question": "Will the team likely develop a good product?",
            "answer": "yes"
        },
        {
            "id": 10,
            "context": "If Sam trains consistently, he has a good chance of qualifying for the marathon. Sam made a schedule to run every morning and evening to build up endurance. Sam trains regularly for the marathon.",
            "question": "Does Sam stand a strong possibility of qualifying?",
            "answer": "yes"
        }
    ]
}